LICENSE.txt
MANIFEST.in
README.rst
setup.cfg
setup.py
data/data_file
fiveleds/__init__.py
fiveleds.egg-info/PKG-INFO
fiveleds.egg-info/SOURCES.txt
fiveleds.egg-info/dependency_links.txt
fiveleds.egg-info/entry_points.txt
fiveleds.egg-info/requires.txt
fiveleds.egg-info/top_level.txt
sample/__init__.py