Metadata-Version: 1.2
Name: fiveleds
Version: 0.1.0
Summary: Control a LED display
Home-page: UNKNOWN
Author: dococassi
Author-email: dococassi@boukom.com
License: BY-NA-SA
Keywords: LED Display Control
Platform: UNKNOWN
Classifier: Development Status :: 3 - Alpha
Classifier: Intended Audience :: Developers
Classifier: Topic :: Multimedia :: Graphics :: Presentation
Classifier: License :: OSI Approved :: GNU General Public License v3 (GPLv3)
Classifier: Programming Language :: Python :: 3
Classifier: Programming Language :: Python :: 3.3
Classifier: Programming Language :: Python :: 3.4
Classifier: Programming Language :: Python :: 3.5
Requires-Python: >=3
